grdpcli/__init__.py
grdpcli/commands.py
grdpcli/help.py
grdpcli/logger.py
grdpcli/variable.py
grdpcli_test-1.0.11.data/data/__init__.py
grdpcli_test-1.0.11.data/data/commands.py
grdpcli_test-1.0.11.data/data/help.py
grdpcli_test-1.0.11.data/data/variable.py
grdpcli_test-1.0.11.data/data/share/grdpcli/grdpcli/__init__.py
grdpcli_test-1.0.11.data/data/share/grdpcli/grdpcli/commands.py
grdpcli_test-1.0.11.data/data/share/grdpcli/grdpcli/get_reponame
grdpcli_test-1.0.11.data/data/share/grdpcli/grdpcli/help.py
grdpcli_test-1.0.11.data/data/share/grdpcli/grdpcli/logger.py
grdpcli_test-1.0.11.data/data/share/grdpcli/grdpcli/variable.py
grdpcli_test-1.0.11.data/data/share/grdpcli/grdpcli/__pycache__/__init__.cpython-38.pyc
grdpcli_test-1.0.11.data/data/share/grdpcli/grdpcli/__pycache__/__init__.cpython-39.pyc
grdpcli_test-1.0.11.data/data/share/grdpcli/grdpcli/__pycache__/commands.cpython-38.pyc
grdpcli_test-1.0.11.data/data/share/grdpcli/grdpcli/__pycache__/commands.cpython-39.pyc
grdpcli_test-1.0.11.data/data/share/grdpcli/grdpcli/__pycache__/logger.cpython-38.pyc
grdpcli_test-1.0.11.data/data/share/grdpcli/grdpcli/__pycache__/logger.cpython-39.pyc
grdpcli_test-1.0.11.data/data/share/grdpcli/grdpcli/__pycache__/variable.cpython-38.pyc
grdpcli_test-1.0.11.data/data/share/grdpcli/grdpcli/__pycache__/variable.cpython-39.pyc
grdpcli_test-1.0.11.data/scripts/grdp
grdpcli_test-1.0.11.dist-info/METADATA
grdpcli_test-1.0.11.dist-info/WHEEL
grdpcli_test-1.0.11.dist-info/top_level.txt
grdpcli_test-1.0.11.dist-info/RECORD
